CHANGES
LICENSE
MANIFEST.in
README.rst
fabfile.py
setup.py
docs/.gitignore
docs/Makefile
docs/conf.py
docs/index.rst
docs/make.bat
example/.gitignore
example/app.py
example/static/style1.css
example/static/style2.css
example/templates/index.html
src/flask_assets.py
src/Flask_Assets2.egg-info/PKG-INFO
src/Flask_Assets2.egg-info/SOURCES.txt
src/Flask_Assets2.egg-info/dependency_links.txt
src/Flask_Assets2.egg-info/entry_points.txt
src/Flask_Assets2.egg-info/not-zip-safe
src/Flask_Assets2.egg-info/requires.txt
src/Flask_Assets2.egg-info/top_level.txt
tests/__init__.py
tests/helpers.py
tests/test_config.py
tests/test_env.py
tests/test_integration.py
tests/test_script.py
tests/test_module/__init__.py
tests/test_module/static/README